[
  {
    "id": "1",
    "title": "Cozy Modern Apartment",
    "description": "A cozy apartment in the city center with great views.",
    "price_per_night": 120,
    "city": "New York",
    "country": "USA",
    "image": "https://images.unsplash.com/photo-1502672260266-1c1ef2d93688",
    "rating": 4.7,
    "reviews_count": 134,
    "category": "apartment",
    "host_name": "John Doe",
    "is_superhost": true
  },
  {
    "id": "2",
    "title": "Luxury Beach House",
    "description": "Beautiful home near the beach with private pool.",
    "price_per_night": 320,
    "city": "Miami",
    "country": "USA",
    "image": "https://images.unsplash.com/photo-1505691938895-1758d7feb511",
    "rating": 4.9,
    "reviews_count": 98,
    "category": "home",
    "host_name": "Sarah Lee",
    "is_superhost": true
  },
  {
    "id": "3",
    "title": "Downtown Studio Apartment",
    "description": "Compact studio perfect for solo travelers.",
    "price_per_night": 90,
    "city": "London",
    "country": "UK",
    "image": "https://images.unsplash.com/photo-1493809842364-78817add7ffb",
    "rating": 4.5,
    "reviews_count": 67,
    "category": "apartment",
    "host_name": "Emma Watson",
    "is_superhost": false
  },
  {
    "id": "4",
    "title": "5-Star Luxury Hotel Room",
    "description": "Premium hotel room with city skyline view.",
    "price_per_night": 450,
    "city": "Dubai",
    "country": "UAE",
    "image": "https://images.unsplash.com/photo-1566073771259-6a8506099945",
    "rating": 4.8,
    "reviews_count": 210,
    "category": "hotel",
    "host_name": "Grand Hotel",
    "is_superhost": true
  },
  {
    "id": "5",
    "title": "Mountain View Cabin",
    "description": "Peaceful home in the mountains.",
    "price_per_night": 180,
    "city": "Denver",
    "country": "USA",
    "image": "https://images.unsplash.com/photo-1449157291145-7efd050a4d0e",
    "rating": 4.6,
    "reviews_count": 88,
    "category": "home",
    "host_name": "Mike Ross",
    "is_superhost": false
  },
  {
    "id": "6",
    "title": "Minimalist Apartment",
    "description": "Clean and modern apartment with minimalist design.",
    "price_per_night": 110,
    "city": "Tokyo",
    "country": "Japan",
    "image": "https://images.unsplash.com/photo-1507089947368-19c1da9775ae",
    "rating": 4.4,
    "reviews_count": 55,
    "category": "apartment",
    "host_name": "Akira Tanaka",
    "is_superhost": false
  },
  {
    "id": "7",
    "title": "Boutique Hotel Suite",
    "description": "Stylish boutique hotel in downtown.",
    "price_per_night": 260,
    "city": "Paris",
    "country": "France",
    "image": "https://images.unsplash.com/photo-1521783988139-893ce9a0d0ef",
    "rating": 4.7,
    "reviews_count": 120,
    "category": "hotel",
    "host_name": "Paris Boutique",
    "is_superhost": true
  },
  {
    "id": "8",
    "title": "Family Home with Garden",
    "description": "Spacious home perfect for families.",
    "price_per_night": 200,
    "city": "Toronto",
    "country": "Canada",
    "image": "https://images.unsplash.com/photo-1568605114967-8130f3a36994",
    "rating": 4.6,
    "reviews_count": 75,
    "category": "home",
    "host_name": "David Smith",
    "is_superhost": false
  },
  {
    "id": "9",
    "title": "City Center Apartment",
    "description": "Stay close to everything in this central apartment.",
    "price_per_night": 140,
    "city": "Berlin",
    "country": "Germany",
    "image": "https://images.unsplash.com/photo-1493666438817-866a91353ca9",
    "rating": 4.5,
    "reviews_count": 60,
    "category": "apartment",
    "host_name": "Anna Müller",
    "is_superhost": false
  },
  {
    "id": "10",
    "title": "Resort Hotel Room",
    "description": "Relaxing hotel stay with resort amenities.",
    "price_per_night": 380,
    "city": "Bali",
    "country": "Indonesia",
    "image": "https://images.unsplash.com/photo-1501117716987-c8e1ecb2102e",
    "rating": 4.9,
    "reviews_count": 190,
    "category": "hotel",
    "host_name": "Bali Resort",
    "is_superhost": true
  },
  {
    "id": "11",
    "title": "Modern Loft Apartment",
    "description": "Open-space loft with industrial style.",
    "price_per_night": 160,
    "city": "Chicago",
    "country": "USA",
    "image": "https://images.unsplash.com/photo-1494526585095-c41746248156",
    "rating": 4.6,
    "reviews_count": 102,
    "category": "apartment",
    "host_name": "Chris Evans",
    "is_superhost": true
  },
  {
    "id": "12",
    "title": "Lake House Retreat",
    "description": "Beautiful home by the lake.",
    "price_per_night": 250,
    "city": "Zurich",
    "country": "Switzerland",
    "image": "https://images.unsplash.com/photo-1505693416388-ac5ce068fe85",
    "rating": 4.8,
    "reviews_count": 77,
    "category": "home",
    "host_name": "Lukas Meier",
    "is_superhost": true
  },
  {
    "id": "13",
    "title": "Budget Hotel Room",
    "description": "Affordable stay with essential amenities.",
    "price_per_night": 80,
    "city": "Bangkok",
    "country": "Thailand",
    "image": "https://images.unsplash.com/photo-1551882547-ff40c63fe5fa",
    "rating": 4.2,
    "reviews_count": 140,
    "category": "hotel",
    "host_name": "Bangkok Stay",
    "is_superhost": false
  },
  {
    "id": "14",
    "title": "Charming Countryside Home",
    "description": "Quiet home surrounded by nature.",
    "price_per_night": 170,
    "city": "Tuscany",
    "country": "Italy",
    "image": "https://images.unsplash.com/photo-1472224371017-08207f84aaae",
    "rating": 4.7,
    "reviews_count": 90,
    "category": "home",
    "host_name": "Giovanni Rossi",
    "is_superhost": true
  },
  {
    "id": "15",
    "title": "Compact City Apartment",
    "description": "Perfect for short stays in the city.",
    "price_per_night": 100,
    "city": "Seoul",
    "country": "South Korea",
    "image": "https://images.unsplash.com/photo-1502005229762-cf1b2da7c5d6",
    "rating": 4.3,
    "reviews_count": 58,
    "category": "apartment",
    "host_name": "Kim Lee",
    "is_superhost": false
  },
  {
    "id": "16",
    "title": "Luxury Hotel Suite",
    "description": "Top-tier hotel suite with premium services.",
    "price_per_night": 500,
    "city": "Singapore",
    "country": "Singapore",
    "image": "https://images.unsplash.com/photo-1542314831-068cd1dbfeeb",
    "rating": 4.9,
    "reviews_count": 220,
    "category": "hotel",
    "host_name": "SG Luxury",
    "is_superhost": true
  },
  {
    "id": "17",
    "title": "Urban Home Stay",
    "description": "Comfortable home in the city suburbs.",
    "price_per_night": 150,
    "city": "Sydney",
    "country": "Australia",
    "image": "https://images.unsplash.com/photo-1512917774080-9991f1c4c750",
    "rating": 4.6,
    "reviews_count": 66,
    "category": "home",
    "host_name": "Olivia Brown",
    "is_superhost": false
  },
  {
    "id": "18",
    "title": "Penthouse Apartment",
    "description": "Luxury apartment with rooftop view.",
    "price_per_night": 350,
    "city": "Los Angeles",
    "country": "USA",
    "image": "https://images.unsplash.com/photo-1501183638710-841dd1904471",
    "rating": 4.8,
    "reviews_count": 143,
    "category": "apartment",
    "host_name": "Ryan Gosling",
    "is_superhost": true
  },
  {
    "id": "19",
    "title": "Eco-Friendly Home",
    "description": "Sustainable home with modern amenities.",
    "price_per_night": 190,
    "city": "Copenhagen",
    "country": "Denmark",
    "image": "https://images.unsplash.com/photo-1499951360447-b19be8fe80f5",
    "rating": 4.7,
    "reviews_count": 80,
    "category": "home",
    "host_name": "Lars Jensen",
    "is_superhost": true
  },
  {
    "id": "20",
    "title": "Classic Hotel Room",
    "description": "Comfortable hotel stay in the city.",
    "price_per_night": 210,
    "city": "Rome",
    "country": "Italy",
    "image": "https://images.unsplash.com/photo-1566665797739-1674de7a421a",
    "rating": 4.5,
    "reviews_count": 110,
    "category": "hotel",
    "host_name": "Rome Suites",
    "is_superhost": false
  }
]